odoo/addons/l10n_es_aeat_mod390/README.rst
odoo/addons/l10n_es_aeat_mod390/__init__.py
odoo/addons/l10n_es_aeat_mod390/__manifest__.py
odoo/addons/l10n_es_aeat_mod390/data/aeat_export_mod390_2019_main_data.xml
odoo/addons/l10n_es_aeat_mod390/data/aeat_export_mod390_2019_sub01_data.xml
odoo/addons/l10n_es_aeat_mod390/data/aeat_export_mod390_2019_sub02_data.xml
odoo/addons/l10n_es_aeat_mod390/data/aeat_export_mod390_2019_sub03_data.xml
odoo/addons/l10n_es_aeat_mod390/data/aeat_export_mod390_2019_sub04_data.xml
odoo/addons/l10n_es_aeat_mod390/data/aeat_export_mod390_2019_sub05_data.xml
odoo/addons/l10n_es_aeat_mod390/data/aeat_export_mod390_2019_sub06_data.xml
odoo/addons/l10n_es_aeat_mod390/data/aeat_export_mod390_2019_sub07_data.xml
odoo/addons/l10n_es_aeat_mod390/data/aeat_export_mod390_2019_sub08_data.xml
odoo/addons/l10n_es_aeat_mod390/data/tax_code_map_mod390_data.xml
odoo/addons/l10n_es_aeat_mod390/data/2021/aeat.model.export.config.csv
odoo/addons/l10n_es_aeat_mod390/data/2021/aeat.model.export.config.line.csv
odoo/addons/l10n_es_aeat_mod390/data/2022/aeat.model.export.config.csv
odoo/addons/l10n_es_aeat_mod390/data/2022/aeat.model.export.config.line.csv
odoo/addons/l10n_es_aeat_mod390/data/2023/aeat.model.export.config.csv
odoo/addons/l10n_es_aeat_mod390/data/2023/aeat.model.export.config.line.csv
odoo/addons/l10n_es_aeat_mod390/docs/dr390e2022.xlsx
odoo/addons/l10n_es_aeat_mod390/docs/instr390.pdf
odoo/addons/l10n_es_aeat_mod390/i18n/ca.po
odoo/addons/l10n_es_aeat_mod390/i18n/es.po
odoo/addons/l10n_es_aeat_mod390/i18n/l10n_es_aeat_mod390.pot
odoo/addons/l10n_es_aeat_mod390/models/__init__.py
odoo/addons/l10n_es_aeat_mod390/models/mod390.py
odoo/addons/l10n_es_aeat_mod390/readme/CONTRIBUTORS.rst
odoo/addons/l10n_es_aeat_mod390/readme/DESCRIPTION.rst
odoo/addons/l10n_es_aeat_mod390/readme/INSTALL.rst
odoo/addons/l10n_es_aeat_mod390/readme/ROADMAP.rst
odoo/addons/l10n_es_aeat_mod390/readme/USAGE.rst
odoo/addons/l10n_es_aeat_mod390/security/ir.model.access.csv
odoo14_addon_l10n_es_aeat_mod390-14.0.3.4.0.dist-info/METADATA
odoo14_addon_l10n_es_aeat_mod390-14.0.3.4.0.dist-info/WHEEL
odoo14_addon_l10n_es_aeat_mod390-14.0.3.4.0.dist-info/top_level.txt
odoo14_addon_l10n_es_aeat_mod390-14.0.3.4.0.dist-info/RECORD
